{
  "collapse-filter": true,
  "search": "",
  "showTags": false,
  "showAttachments": false,
  "hideUnresolved": false,
  "showOrphans": true,
  "collapse-color-groups": true,
  "colorGroups": [
    {"query": "tag:#FX", "color": "#d91d1d"},
    {"query": "tag:#SNS", "color": "#1da1f2"},
    {"query": "tag:#経営", "color": "#18a339"},
    {"query": "tag:#介護", "color": "#9b59b6"},
    {"query": "tag:#学習", "color": "#f39c12"},
    {"query": "tag:#師匠の教え", "color": "#e74c3c"}
  ],
  "collapse-display": true,
  "showArrow": false,
  "textFadeMultiplier": 0,
  "nodeSizeMultiplier": 1,
  "lineSizeMultiplier": 1,
  "collapse-forces": true,
  "centerStrength": 0.518713248970312,
  "repelStrength": 10,
  "linkStrength": 1,
  "linkDistance": 250,
  "scale": 0.9999999999999993,
  "close": true
}